jiraph/__init__.py
jiraph-0.0.1.dist-info/METADATA
jiraph-0.0.1.dist-info/RECORD
jiraph-0.0.1.dist-info/WHEEL
jiraph-0.0.1.dist-info/top_level.txt
