Metadata-Version: 2.1
Name: jiraph
Version: 0.0.1
Summary: JIRA python helper
Home-page: http://github.com/ramonfm/jiraph
Author: Ramón Fernández
Author-email: ramon@nospam.com
License: MIT
Platform: UNKNOWN
Classifier: Programming Language :: Python :: 3
Classifier: License :: OSI Approved :: GNU Affero General Public License v3
Classifier: Operating System :: OS Independent
